twilkit/__init__.py
twilkit/core.py
twilkit/ADVfile_manager/__init__.py
twilkit/ADVfile_manager/core.py
twilkit/extra_tools/__init__.py
twilkit/extra_tools/core.py
twilkit/pyproj_inspector/__init__.py
twilkit/pyproj_inspector/build_utils.py
twilkit/pyproj_inspector/cli.py
twilkit/pyproj_inspector/inspector.py
twilkit/pyproj_inspector/packaging_utils.py
twilkit-2.0.0.dist-info/licenses/LICENSE
twilkit-2.0.0.dist-info/METADATA
twilkit-2.0.0.dist-info/WHEEL
twilkit-2.0.0.dist-info/top_level.txt
twilkit-2.0.0.dist-info/RECORD
