Metadata-Version: 2.4
Name: twilkit
Version: 2.0.0
Summary: Lightweight Python toolkit: validators, colors, decorators, and FlexVar
Author: Avi Twil
License: MIT License
Project-URL: Homepage, https://github.com/avitwil/twilkit
Project-URL: Repository, https://github.com/avitwil/twilkit
Project-URL: Issues, https://github.com/avitwil/twilkit/issues
Keywords: validation,decorators,colors,ansi,toolkit,utilities
Classifier: Development Status :: 4 - Beta
Classifier: Intended Audience :: Developers
Classifier: License :: OSI Approved :: MIT License
Classifier: Programming Language :: Python :: 3
Classifier: Programming Language :: Python :: 3.10
Classifier: Programming Language :: Python :: 3.11
Classifier: Programming Language :: Python :: 3.12
Classifier: Operating System :: OS Independent
Classifier: Topic :: Software Development :: Libraries
Classifier: Topic :: Utilities
Requires-Python: >=3.10
License-File: LICENSE
Provides-Extra: extra-tools
Requires-Dist: ADVfile-manager>=1.3.1; extra == "extra-tools"
Dynamic: license-file
